setup.py
ohs/__init__.py
ohs.egg-info/PKG-INFO
ohs.egg-info/SOURCES.txt
ohs.egg-info/dependency_links.txt
ohs.egg-info/top_level.txt