Metadata-Version: 1.0
Name: ohs
Version: 0.0.0.dev0
Summary: Oregon Historical Society (namespace package)
Home-page: http://ohs.org/
Author: Wyatt Baldwin
Author-email: wbaldwin@pdx.edu
License: UNKNOWN
Platform: UNKNOWN
